[
  {
    "full_name": "keephq/keep",
    "stargazers_count": 9238,
    "open_issues_count": 218,
    "forks_count": 831
  },
  {
    "full_name": "Ompluscator/go-promise",
    "stargazers_count": 9,
    "open_issues_count": 0,
    "forks_count": 3
  },
  {
    "full_name": "chebyrash/promise",
    "stargazers_count": 393,
    "open_issues_count": 0,
    "forks_count": 37
  },
  {
    "full_name": "lllyasviel/Omost",
    "stargazers_count": 7486,
    "open_issues_count": 85,
    "forks_count": 427
  },
  {
    "full_name": "PatnosDD/Cuphead-PS-VITA",
    "stargazers_count": 119,
    "open_issues_count": 0,
    "forks_count": 3
  },
  {
    "full_name": "gdquest-demos/godot-3d-mannequin",
    "stargazers_count": 938,
    "open_issues_count": 13,
    "forks_count": 74
  },
  {
    "full_name": "PatnosDD/Hollow-Knight-PsVita",
    "stargazers_count": 82,
    "open_issues_count": 0,
    "forks_count": 2
  },
  {
    "full_name": "traefik/mesh",
    "stargazers_count": 2048,
    "open_issues_count": 42,
    "forks_count": 142
  }
]